ioos_pkg_skeleton/__init__.py
ioos_pkg_skeleton/_version.py
ioos_pkg_skeleton/ioos_pkg_skeleton.py
ioos_pkg_skeleton-1.0.0.dist-info/LICENSE.txt
ioos_pkg_skeleton-1.0.0.dist-info/METADATA
ioos_pkg_skeleton-1.0.0.dist-info/WHEEL
ioos_pkg_skeleton-1.0.0.dist-info/top_level.txt
ioos_pkg_skeleton-1.0.0.dist-info/RECORD
