Metadata-Version: 2.1
Name: ioos-pkg-skeleton
Version: 1.0.0
Summary: My Awesome module
Home-page: https://github.com/ioos/ioos-python-package-skeleton
Author: AUTHOR NAME
Author-email: AUTHOR@EMAIL.COM
License: BSD-3-Clause
Platform: UNKNOWN
Classifier: Development Status :: 5 - Production/Stable
Classifier: Intended Audience :: Science/Research
Classifier: Operating System :: OS Independent
Classifier: License :: OSI Approved :: BSD License
Classifier: Programming Language :: Python
Classifier: Programming Language :: Python :: 3
Classifier: Programming Language :: Python :: 3.6
Classifier: Programming Language :: Python :: 3.7
Classifier: Programming Language :: Python :: 3.8
Classifier: Topic :: Scientific/Engineering
Requires-Python: >=3.6
Requires-Dist: numpy
Requires-Dist: requests
